README.md
setup.py
nonebot/__init__.py
nonebot/argparse.py
nonebot/default_config.py
nonebot/exceptions.py
nonebot/helpers.py
nonebot/log.py
nonebot/message.py
nonebot/natural_language.py
nonebot/notice_request.py
nonebot/permission.py
nonebot/plugin.py
nonebot/sched.py
nonebot/session.py
nonebot/typing.py
nonebot.egg-info/PKG-INFO
nonebot.egg-info/SOURCES.txt
nonebot.egg-info/dependency_links.txt
nonebot.egg-info/requires.txt
nonebot.egg-info/top_level.txt
nonebot/command/__init__.py
nonebot/command/group.py
nonebot/command/group.pyi
nonebot/command/argfilter/__init__.py
nonebot/command/argfilter/controllers.py
nonebot/command/argfilter/converters.py
nonebot/command/argfilter/extractors.py
nonebot/command/argfilter/validators.py
nonebot/experimental/__init__.py
nonebot/experimental/permission.py
nonebot/experimental/plugin.py
nonebot/plugins/__init__.py
nonebot/plugins/base.py