Metadata-Version: 2.1
Name: nonebot
Version: 1.8.0
Summary: An asynchronous QQ bot framework based on CoolQ.
Home-page: https://github.com/nonebot/nonebot
Author: NoneBot Team
License: MIT License
Platform: any
Classifier: Development Status :: 5 - Production/Stable
Classifier: Framework :: Robot Framework
Classifier: Framework :: Robot Framework :: Library
Classifier: License :: OSI Approved :: MIT License
Classifier: Operating System :: OS Independent
Classifier: Programming Language :: Python :: 3
Requires-Python: >=3.7
Provides-Extra: scheduler
